sphinxcontrib/__init__.py
sphinxcontrib/swaggersphinx/__init__.py
sphinxcontrib/swaggersphinx/directive.py
sphinxcontrib_swaggersphinx-0.1.0.dist-info/DESCRIPTION.rst
sphinxcontrib_swaggersphinx-0.1.0.dist-info/METADATA
sphinxcontrib_swaggersphinx-0.1.0.dist-info/RECORD
sphinxcontrib_swaggersphinx-0.1.0.dist-info/WHEEL
sphinxcontrib_swaggersphinx-0.1.0.dist-info/metadata.json
sphinxcontrib_swaggersphinx-0.1.0.dist-info/top_level.txt
