Metadata-Version: 2.0
Name: sphinxcontrib-swaggersphinx
Version: 0.1.0
Summary: Convert swagger JSON files to tables in Sphinx
Home-page: https://github.com/timster/sphinxcontrib-swaggersphinx
Author: Tim Shaffer
Author-email: timshaffer@me.com
License: MIT
Keywords: sphinx swagger documentation
Platform: UNKNOWN
Classifier: Development Status :: 3 - Alpha
Classifier: Intended Audience :: Developers
Classifier: Topic :: Database :: Front-Ends
Classifier: License :: OSI Approved :: MIT License
Classifier: Programming Language :: Python :: 3.3
Classifier: Programming Language :: Python :: 3.4
Classifier: Programming Language :: Python :: 3.5
